{
  "gitSyncId": "67a2400b3e12e107acd1a186_c6c616d9-40e6-4fed-806f-7d395aa1cfb6",
  "id": "Main_TotalPayout",
  "pluginId": "postgres-plugin",
  "pluginType": "DB",
  "unpublishedAction": {
    "actionConfiguration": {
      "body": "SELECT \n  COALESCE((\n    SELECT SUM(amount)\n    FROM cashoperations\n    WHERE direction = 'out'\n  \n      \n      AND operation_group = {{Contracts.selectedRow.operation_group}}::uuid\n   \n  ), 0) AS total_payout;\n",
      "encodeParamsToggle": true,
      "paginationType": "NONE",
      "pluginSpecifiedTemplates": [
        {
          "value": true
        }
      ],
      "timeoutInMillisecond": 10000
    },
    "confirmBeforeExecute": false,
    "datasource": {
      "id": "WieczorekAssets",
      "isAutoGenerated": false,
      "name": "WieczorekAssets",
      "pluginId": "postgres-plugin"
    },
    "dynamicBindingPathList": [
      {
        "key": "body"
      }
    ],
    "executeOnLoad": true,
    "name": "TotalPayout",
    "pageId": "Main",
    "userSetOnLoad": false
  }
}